Metadata-Version: 1.0
Name: easydistributions
Version: 0.1
Summary: Easy to use distributions, such as Gaussian, Binomial added with utility features
Home-page: UNKNOWN
Author: UNKNOWN
Author-email: UNKNOWN
License: UNKNOWN
Platform: UNKNOWN
